<RS>{"type":"FeatureCollection", "externalId": 1, "features":[{"type":"Feature","geometry":{"type":"Point","coordinates":[-82.9908295,42.435009]},"properties":{"address":"13001 East Seven Mile","latitude":"42.435009","longitude":"-82.9908295","business_name":"Lions Auto Sales"}}]}
<RS>{"type":"FeatureCollection", "externalId": 2, "features":[{"type":"Feature","geometry":{"type":"Point","coordinates":[-82.94074,42.42207]},"properties":{"address":"10709 Morang","latitude":"42.42207","longitude":"-82.94074","business_name":"Great Lakes Investment"}}]}
<RS>{"type":"FeatureCollection", "externalId": 1, "features":[{"type":"Feature","geometry":{"type":"Point","coordinates":[-83.129097,42.3111]},"properties":{"address":"8118 West Vernor","latitude":"42.3111","longitude":"-83.129097","business_name":"St. Gabriel Church"}}]}
